cns/__init__.py
console_novel_system-0.1.8.dist-info/licenses/LICENSE
console_novel_system-0.1.8.dist-info/licenses/LICENSE.md
console_novel_system-0.1.8.dist-info/METADATA
console_novel_system-0.1.8.dist-info/WHEEL
console_novel_system-0.1.8.dist-info/top_level.txt
console_novel_system-0.1.8.dist-info/RECORD
