Metadata-Version: 2.4
Name: console-novel-system
Version: 0.1.8
Summary: A system to help create "visual novels", but run in the console.
Author: Error Dev
Author-email: 3rr0r.d3v@gmail.com
License: Proprietary
Classifier: Programming Language :: Python
Classifier: Environment :: Console
Classifier: Natural Language :: English
Requires-Python: >=3.6
License-File: LICENSE.md
License-File: LICENSE
Requires-Dist: requests
Requires-Dist: packaging
Requires-Dist: colorama
Dynamic: author
Dynamic: author-email
Dynamic: classifier
Dynamic: description
Dynamic: description-content-type
Dynamic: license
Dynamic: license-file
Dynamic: requires-dist
Dynamic: requires-python
Dynamic: summary
